LICENSE
README.md
setup.py
ani_cache/VERSION
ani_cache/__init__.py
ani_cache/exceptions.py
ani_cache/fastani.py
ani_cache/logger.py
ani_cache/main.py
ani_cache/utils.py
ani_cache.egg-info/PKG-INFO
ani_cache.egg-info/SOURCES.txt
ani_cache.egg-info/dependency_links.txt
ani_cache.egg-info/top_level.txt
ani_cache/tests/test_utils.py
bin/ani_cache